{
  "fill" : {
    "automatic-gradient" : "srgb:0.00000,0.47843,1.00000,1.00000"
  },
  "groups" : [
    {
      "blur-material" : null,
      "layers" : [
        {
          "fill" : "automatic",
          "hidden" : false,
          "image-name" : "Combined Shape 2.png",
          "name" : "Combined Shape 2",
          "opacity" : 0.8,
          "position" : {
            "scale" : 1,
            "translation-in-points" : [
              -0.2031606136985894,
              14.634117754482261
            ]
          }
        }
      ],
      "lighting" : "combined",
      "opacity" : 0.8,
      "position-specializations" : [
        {
          "value" : {
            "scale" : 1,
            "translation-in-points" : [
              0,
              0
            ]
          }
        },
        {
          "idiom" : "watchOS",
          "value" : {
            "scale" : 0.9,
            "translation-in-points" : [
              0,
              0
            ]
          }
        }
      ],
      "shadow" : {
        "kind" : "neutral",
        "opacity" : 1
      },
      "specular" : true,
      "translucency" : {
        "enabled" : false,
        "value" : 0.2
      }
    }
  ],
  "supported-platforms" : {
    "circles" : [
      "watchOS"
    ],
    "squares" : "shared"
  }
}